{
	"SPRING": {
		"1st": {
			"moves": 50,
			"name": "Blue"
		},
		"2nd": {
			"moves": 55,
			"name": "Red"
		},
		"3rd": {
			"moves": 60,
			"name": "aaaaa"
		},
		"4th": {
			"moves": 65,
			"name": "Emma"
		},
		"5th": {
			"moves": 70,
			"name": "EEEEE"
		}
	},
	"SUMMER": {
		"1st": {
			"moves": 50,
			"name": "Saint"
		},
		"2nd": {
			"moves": 55,
			"name": "Suna"
		},
		"3rd": {
			"moves": 60,
			"name": "Emma"
		},
		"4th": {
			"moves": 65,
			"name": "Omar"
		},
		"5th": {
			"moves": 70,
			"name": "Shofi"
		}
	},
	"WINTER": {
		"1st": {
			"moves": 50,
			"name": "Saint"
		},
		"2nd": {
			"moves": 55,
			"name": "Suna"
		},
		"3rd": {
			"moves": 60,
			"name": "Emma"
		},
		"4th": {
			"moves": 65,
			"name": "Omar"
		},
		"5th": {
			"moves": 70,
			"name": "Shofi"
		}
	}
}
